ldifdiff.py
ldifdiff-1.0.0.dist-info/METADATA
ldifdiff-1.0.0.dist-info/WHEEL
ldifdiff-1.0.0.dist-info/entry_points.txt
ldifdiff-1.0.0.dist-info/top_level.txt
ldifdiff-1.0.0.dist-info/RECORD
