Metadata-Version: 2.1
Name: ldifdiff
Version: 1.0.0
Summary: Tool for comparing LDIF files
License: MIT
Project-URL: repository, https://github.com/pfptcommunity/ldifdiff
Requires-Python: >3.9
Requires-Dist: ldif
Requires-Dist: colorama
